<Properties StartupConfiguration="{5B5C8EC3-B378-491A-847F-1AA2A2BB768D}|Default">
  <MultiItemStartupConfigurations />
  <MonoDevelop.Ide.DebuggingService.Breakpoints>
    <BreakpointStore />
  </MonoDevelop.Ide.DebuggingService.Breakpoints>
  <MonoDevelop.Ide.Workspace ActiveConfiguration="Debug" />
  <Xamarin.Addins.Core.Project ActiveDebugTarget="Android.pixel_2_pie_9_0_-_api_28" />
  <MonoDevelop.MonoDroid LastDeploySdkVersion="12.3.0.3" />
  <MonoDevelop.Ide.Workbench ActiveDocument="P4Travia/MainActivity.cs">
    <Files>
      <File FileName="P4Travia/Resources/layout/bottom_nav_bar.xml" Line="33" Column="66" />
      <File FileName="P4Travia/MainActivity.cs" Line="1" Column="1" />
    </Files>
    <Pads>
      <Pad Id="ProjectPad">
        <State name="__root__">
          <Node name="P4Travia" expanded="True">
            <Node name="P4Travia" expanded="True">
              <Node name="Activities" expanded="True" />
              <Node name="Fragments" expanded="True" />
              <Node name="Resources" expanded="True">
                <Node name="mipmap-anydpi-v26" expanded="True" />
                <Node name="mipmap-xhdpi" expanded="True" />
                <Node name="mipmap-xxhdpi" expanded="True" />
                <Node name="mipmap-xxxhdpi" expanded="True" />
                <Node name="values" expanded="True" />
              </Node>
              <Node name="Signup" expanded="True" />
              <Node name="MainActivity.cs" selected="True" />
            </Node>
          </Node>
        </State>
      </Pad>
      <Pad Id="MonoDevelop.Debugger.WatchPad">
        <State />
      </Pad>
    </Pads>
  </MonoDevelop.Ide.Workbench>
  <MonoDevelop.Ide.DebuggingService.PinnedWatches />
  <MonoDevelop.Ide.ItemProperties.P4Travia AndroidDesignerPreferredTheme="AppTheme" PreferredExecutionTarget="Android.pixel_2_pie_9_0_-_api_28" AndroidDesignerPreferredDevice="pixel_3" />
</Properties>